napari_camera/__init__.py
napari_camera/_widget.py
napari_camera/napari.yaml
napari_camera-0.0.3.dist-info/licenses/LICENSE
napari_camera-0.0.3.dist-info/METADATA
napari_camera-0.0.3.dist-info/WHEEL
napari_camera-0.0.3.dist-info/entry_points.txt
napari_camera-0.0.3.dist-info/top_level.txt
napari_camera-0.0.3.dist-info/RECORD
