Metadata-Version: 2.4
Name: napari-camera
Version: 0.0.3
Summary: Provides control over camera settings and allows saving and loading full viewer configurations to easily recreate and share consistent visual perspectives.
Author: Lars Krämer
Author-email: lars.kraemer@dkfz-heidelberg.de
License: 
Project-URL: Homepage, https://github.com/MIC-DKFZ/napari-camera
Project-URL: Code, https://github.com/MIC-DKFZ/napari-camera
Classifier: Development Status :: 2 - Pre-Alpha
Classifier: Framework :: napari
Classifier: Intended Audience :: Developers
Classifier: License :: OSI Approved :: Apache Software License
Classifier: Operating System :: OS Independent
Classifier: Programming Language :: Python
Classifier: Programming Language :: Python :: 3
Classifier: Programming Language :: Python :: 3 :: Only
Classifier: Programming Language :: Python :: 3.9
Classifier: Programming Language :: Python :: 3.10
Classifier: Programming Language :: Python :: 3.11
Classifier: Programming Language :: Python :: 3.12
Classifier: Topic :: Scientific/Engineering :: Image Processing
Requires-Python: >=3.9
License-File: LICENSE
Requires-Dist: napari_toolkit
Requires-Dist: qtpy
Provides-Extra: testing
Requires-Dist: tox; extra == "testing"
Requires-Dist: pytest; extra == "testing"
Requires-Dist: pytest-cov; extra == "testing"
Requires-Dist: pytest-qt; extra == "testing"
Requires-Dist: napari; extra == "testing"
Requires-Dist: pyqt5; extra == "testing"
Dynamic: license-file
